brickops/__init__.py
brickops/gitutils.py
brickops/py.typed
brickops/databricks/__init__.py
brickops/databricks/api.py
brickops/databricks/context.py
brickops/databricks/username.py
brickops/datamesh/__init__.py
brickops/datamesh/naming.py
brickops/datamesh/cfg/__init__.py
brickops/datamesh/parsepath/__init__.py
brickops/datamesh/parsepath/extractname.py
brickops/datamesh/parsepath/parse.py
brickops/datamesh/parserepath/__init__.py
brickops/datamesh/parserepath/parse.py
brickops/dataops/__init__.py
brickops/dataops/job.py
brickops/dataops/pipeline.py
brickops/dataops/deploy/__init__.py
brickops/dataops/deploy/autojob.py
brickops/dataops/deploy/autopipeline.py
brickops/dataops/deploy/nbpath.py
brickops/dataops/deploy/readconfig.py
brickops/dataops/deploy/repo.py
brickops/dataops/deploy/job/buildconfig/__init__.py
brickops/dataops/deploy/job/buildconfig/build.py
brickops/dataops/deploy/job/buildconfig/clusters.py
brickops/dataops/deploy/job/buildconfig/enrichtasks.py
brickops/dataops/deploy/job/buildconfig/job_config.py
brickops/dataops/deploy/pipeline/buildconfig/__init__.py
brickops/dataops/deploy/pipeline/buildconfig/build.py
brickops/dataops/deploy/pipeline/buildconfig/enrichtasks.py
brickops/dataops/deploy/pipeline/buildconfig/pipeline_config.py
brickops/tools/__init__.py
brickops/tools/cleanup_tools.py
brickops-0.3.18.dist-info/METADATA
brickops-0.3.18.dist-info/WHEEL
brickops-0.3.18.dist-info/top_level.txt
brickops-0.3.18.dist-info/RECORD
