Metadata-Version: 2.4
Name: brickops
Version: 0.3.18
Summary: Knowit's dataops library - simplifying building data pipelines in Databricks, for both testing and production use cases. The package enables a workflow where users write their code in notebooks, and then deploy them to a Databricks workspace without stepping on each other's toes.
Requires-Python: >=3.10
Requires-Dist: pyyaml>=6.0.2
Requires-Dist: requests>=2.32.3
